plotnik/__init__.py
plotnik/_version.py
plotnik/drawing.py
plotnik/global_drawing.py
plotnik/processes.py
plotnik-1.dist-info/LICENSE
plotnik-1.dist-info/METADATA
plotnik-1.dist-info/WHEEL
plotnik-1.dist-info/top_level.txt
plotnik-1.dist-info/RECORD
